pytleap/VERSION
pytleap/__init__.py
pytleap/__main__.py
pytleap/client.py
pytleap/eap.py
pytleap/error.py
pytleap/utils.py
pytleap-1.0.1.dist-info/LICENSE
pytleap-1.0.1.dist-info/METADATA
pytleap-1.0.1.dist-info/WHEEL
pytleap-1.0.1.dist-info/top_level.txt
pytleap-1.0.1.dist-info/RECORD
