Metadata-Version: 2.1
Name: pytleap
Version: 1.0.1
Summary: Interface to connect to a TP-Link EAP.
Home-page: https://github.com/chemicalstorm/pytleap
Author: chemicalstorm
Author-email: storm+github@chemicalstorm.org
License: MIT
Download-URL: https://github.com/chemicalstorm/pytleap/archive/1.0.1.zip
Keywords: tp-link eap
Platform: UNKNOWN
Requires-Python: >=3.7
Requires-Dist: aiohttp
